helix/plugins/microarray_templates/VERSION.py
helix/plugins/microarray_templates/__init__.py
doublehelix_microarray_templates-0.0.1a1.dist-info/LICENSE
doublehelix_microarray_templates-0.0.1a1.dist-info/METADATA
doublehelix_microarray_templates-0.0.1a1.dist-info/WHEEL
doublehelix_microarray_templates-0.0.1a1.dist-info/top_level.txt
doublehelix_microarray_templates-0.0.1a1.dist-info/RECORD
