Metadata-Version: 2.1
Name: doublehelix-microarray_templates
Version: 0.0.1a1
Summary: This repository contains the templates for microarray file generator
Author-email: chaplin89 <hello@doublehelix.app>
License: GNU GENERAL PUBLIC LICENSE
Project-URL: Documentation, https://doublehelix.app
Project-URL: homepage, https://doublehelix.app
Project-URL: Repository, https://github.com/DoubleHelixApp/DoubleHelix-Microarray-Templates
Project-URL: Issues, https://github.com/DoubleHelixApp/DoubleHelix-Microarray-Templates/issues
Project-URL: Changelog, https://github.com/DoubleHelixApp/DoubleHelix-Microarray-Templates/releases
Keywords: bioinformatics,genetics,wgs,microarray,science
Classifier: Development Status :: 3 - Alpha
Classifier: Environment :: Console
Classifier: Environment :: X11 Applications :: Qt
Classifier: Environment :: Win32 (MS Windows)
Classifier: Intended Audience :: Developers
Classifier: Intended Audience :: Science/Research
Classifier: License :: OSI Approved :: BSD License
Classifier: License :: OSI Approved :: MIT License
Classifier: Operating System :: OS Independent
Classifier: Programming Language :: Python :: 3.12
Classifier: Topic :: Scientific/Engineering :: Bio-Informatics
License-File: LICENSE
Requires-Dist: setuptools
